iris_system/__init__.py
iris_system/decorators.py
iris_system/iris_database.py
iris_system/iris_recognition.py
iris_system-0.1.0.dist-info/LICENSE.md
iris_system-0.1.0.dist-info/METADATA
iris_system-0.1.0.dist-info/WHEEL
iris_system-0.1.0.dist-info/top_level.txt
iris_system-0.1.0.dist-info/RECORD
