Metadata-Version: 2.1
Name: iris_system
Version: 0.1.0
Summary: Developing a robust tool for iris image analysis and recognition, including planned features such as advanced extraction and comparison of iris data, performance optimization using Random Forest Classifiers over keypoints, improvements for challenging conditions and database control. See for more, https://github.com/elymsyr/iris-recognition.
Home-page: https://github.com/elymsyr/iris-recognition
Author: Orhun Eren Yalçınkaya
Author-email: orhun868@gmail.com
License: MIT
Classifier: Programming Language :: Python :: 3
Classifier: License :: OSI Approved :: MIT License
Classifier: Operating System :: OS Independent
License-File: LICENSE.md
Requires-Dist: numpy ==2.0.2
Requires-Dist: opencv-python ==4.10.0.84
Requires-Dist: matplotlib ==3.9.2
